<?xml version='1.0' encoding='UTF-8' standalone='yes' ?>
<Robot type="FirstInspires-FTC">
    <LynxUsbDevice name="Control Hub Portal" serialNumber="(embedded)" parentModuleAddress="173">
        <LynxModule name="Expansion Hub 2" port="2">
            <NeveRest20Gearmotor name="lift" port="0" />
            <NeveRest60Gearmotor name="spinner" port="1" />
            <NeveRest20Gearmotor name="intake" port="2" />
            <LynxEmbeddedIMU name="imu" port="0" bus="0" />
        </LynxModule>
        <LynxModule name="Control Hub" port="173">
            <NeveRest20Gearmotor name="frontLeft" port="0" />
            <NeveRest20Gearmotor name="backLeft" port="1" />
            <NeveRest20Gearmotor name="frontRight" port="2" />
            <NeveRest20Gearmotor name="backRight" port="3" />
            <Servo name="bucket" port="0" />
            <Servo name="odometryLift" port="1" />
            <Servo name="capper" port="2" />
            <Servo name="grabber" port="3" />
            <LynxEmbeddedIMU name="imu" port="0" bus="0" />
        </LynxModule>
    </LynxUsbDevice>
</Robot>
